[
  {
    "code": "25fh8",
    "manager": {
      "code": "ugdk8",
      "lastName": "Splevings",
      "firstName": "Granny",
      "address": {
        "street": "08822 Tony Trail",
        "city": "Fort Wayne",
        "state": "IN",
        "zip": "46857",
        "country": "US"
      },
      "emails": [
        "gsplevings3@sciencedaily.com",
        "gsplevings3@opensource.org"
      ]
    },
    "address": {
      "street": "14754 Northwestern Place",
      "city": "Norman",
      "state": "OK",
      "zip": "73071",
      "country": "US"
    }
  },
  {
    "code": "f3qy9",
    "manager": {
      "code": "5uc2f",
      "lastName": "McGinney",
      "firstName": "Anabel",
      "address": {
        "street": "0 Golf Course Crossing",
        "city": "Salt Lake City",
        "state": "UT",
        "zip": "84189",
        "country": "US"
      },
      "emails": [
        "amcginney1@blog.com",
        "amcginney1@clickbank.net",
        "amcginney1@tripod.com"
      ]
    },
    "address": {
      "street": "748 Crescent Oaks Center",
      "city": "Norfolk",
      "state": "VA",
      "zip": "23514",
      "country": "US"
    }
  },
  {
    "code": "evm01",
    "manager": {
      "code": "fwk38",
      "lastName": "Wessing",
      "firstName": "Wanids",
      "address": {
        "street": "46 Utah Drive",
        "city": "New York City",
        "state": "NY",
        "zip": "10060",
        "country": "US"
      },
      "emails": [
        "wwessing4@stanford.edu",
        "wwessing4@hatena.ne.jp",
        "wwessing4@archive.org"
      ]
    },
    "address": {
      "street": "1702 Continental Road",
      "city": "El Paso",
      "state": "TX",
      "zip": "79968",
      "country": "US"
    }
  },
  {
    "code": "ctm3n",
    "manager": {
      "code": "c8q41",
      "lastName": "Marval",
      "firstName": "Mel",
      "address": {
        "street": "7 Hooker Crossing",
        "city": "Wilmington",
        "state": "DE",
        "zip": "19892",
        "country": "US"
      },
      "emails": [
        "mmarval7@paypal.com",
        "mmarval7@reddit.com",
        "mmarval7@blogs.com"
      ]
    },
    "address": {
      "street": "48 Fallview Pass",
      "city": "Miami",
      "state": "FL",
      "zip": "33261",
      "country": "US"
    }
  },
  {
    "code": "pjpyq",
    "manager": {
      "code": "jdmus",
      "lastName": "Wildt",
      "firstName": "Doe",
      "address": {
        "street": "1 Ryan Drive",
        "city": "New York City",
        "state": "NY",
        "zip": "10079",
        "country": "US"
      },
      "emails": [
        "dwildt0@instagram.com",
        "dwildt0@reverbnation.com",
        "dwildt0@arstechnica.com",
        "dwildt0@bloomberg.com"
      ]
    },
    "address": {
      "street": "46 Sunfield Circle",
      "city": "Nashville",
      "state": "TN",
      "zip": "37250",
      "country": "US"
    }
  },
  {
    "code": "iaivj",
    "manager": {
      "code": "g87xs",
      "lastName": "Pagel",
      "firstName": "Hermina",
      "address": {
        "street": "61 Anthes Way",
        "city": "Montgomery",
        "state": "AL",
        "zip": "36195",
        "country": "US"
      },
      "emails": []
    },
    "address": {
      "street": "62 Tennyson Circle",
      "city": "Paterson",
      "state": "NJ",
      "zip": "7522",
      "country": "US"
    }
  },
  {
    "code": "8nyko",
    "manager": {
      "code": "snzgx",
      "lastName": "Peniman",
      "firstName": "Alyssa",
      "address": {
        "street": "78044 Ludington Parkway",
        "city": "Fort Wayne",
        "state": "IN",
        "zip": "46852",
        "country": "US"
      },
      "emails": [
        "apeniman9@webs.com",
        "apeniman9@reverbnation.com"
      ]
    },
    "address": {
      "street": "47148 Sugar Alley",
      "city": "Los Angeles",
      "state": "CA",
      "zip": "90035",
      "country": "US"
    }
  },
  {
    "code": "tff70",
    "manager": {
      "code": "z4ck9",
      "lastName": "Gaines",
      "firstName": "Darcy",
      "address": {
        "street": "6 Debs Drive",
        "city": "Portland",
        "state": "OR",
        "zip": "97211",
        "country": "US"
      },
      "emails": [
        "dgaines6@edublogs.org",
        "dgaines6@myspace.com",
        "dgaines6@eepurl.com"
      ]
    },
    "address": {
      "street": "155 Little Fleur Terrace",
      "city": "El Paso",
      "state": "TX",
      "zip": "88574",
      "country": "US"
    }
  },
  {
    "code": "1b5bf",
    "manager": {
      "code": "oq6fn",
      "lastName": "Livings",
      "firstName": "Frances",
      "address": {
        "street": "17 Lotheville Crossing",
        "city": "Louisville",
        "state": "KY",
        "zip": "40220",
        "country": "US"
      },
      "emails": [
        "flivings2@clickbank.net",
        "flivings2@posterous.com"
      ]
    },
    "address": {
      "street": "91793 Duke Trail",
      "city": "Pittsburgh",
      "state": "PA",
      "zip": "15255",
      "country": "US"
    }
  },
  {
    "code": "n5xhl",
    "manager": {
      "code": "8yo0n",
      "lastName": "Chantler",
      "firstName": "Giuditta",
      "address": {
        "street": "1348 School Junction",
        "city": "Tampa",
        "state": "FL",
        "zip": "33686",
        "country": "US"
      },
      "emails": [
        "gchantlera@google.com.au",
        "gchantlera@xinhuanet.com",
        "gchantlera@merriam-webster.com"
      ]
    },
    "address": {
      "street": "4 Dottie Lane",
      "city": "Augusta",
      "state": "GA",
      "zip": "30919",
      "country": "US"
    }
  },
  {
    "code": "ksamo",
    "manager": {
      "code": "v857t",
      "lastName": "Brewis",
      "firstName": "Raddie",
      "address": {
        "street": "5 Prairie Rose Center",
        "city": "Dallas",
        "state": "TX",
        "zip": "75205",
        "country": "US"
      },
      "emails": []
    },
    "address": {
      "street": "6 Pleasure Street",
      "city": "Jacksonville",
      "state": "FL",
      "zip": "32230",
      "country": "US"
    }
  },
  {
    "code": "a7cfq",
    "manager": {
      "code": "5iowx",
      "lastName": "Cogswell",
      "firstName": "Dov",
      "address": {
        "street": "41 Thompson Drive",
        "city": "Atlanta",
        "state": "GA",
        "zip": "30301",
        "country": "US"
      },
      "emails": [
        "dcogswelld@friendfeed.com",
        "dcogswelld@list-manage.com",
        "dcogswelld@sciencedaily.com"
      ]
    },
    "address": {
      "street": "232 Brentwood Avenue",
      "city": "Milwaukee",
      "state": "WI",
      "zip": "53225",
      "country": "US"
    }
  },
  {
    "code": "kget3",
    "manager": {
      "code": "rhksc",
      "lastName": "Bridger",
      "firstName": "Christoper",
      "address": {
        "street": "91 Riverside Lane",
        "city": "Sarasota",
        "state": "FL",
        "zip": "34276",
        "country": "US"
      },
      "emails": [
        "cbridger5@jalbum.net",
        "cbridger5@mac.com"
      ]
    },
    "address": {
      "street": "8 Leroy Lane",
      "city": "Mesa",
      "state": "AZ",
      "zip": "85205",
      "country": "US"
    }
  },
  {
    "code": "ebryi",
    "manager": {
      "code": "8yhjk",
      "lastName": "Brosi",
      "firstName": "Allys",
      "address": {
        "street": "018 Bartillon Avenue",
        "city": "Fresno",
        "state": "CA",
        "zip": "93773",
        "country": "US"
      },
      "emails": [
        "abrosic@google.it",
        "abrosic@ovh.net"
      ]
    },
    "address": {
      "street": "537 Park Meadow Center",
      "city": "Wilmington",
      "state": "NC",
      "zip": "28405",
      "country": "US"
    }
  }
]